cython_cmake/__init__.py
cython_cmake/__main__.py
cython_cmake/_version.py
cython_cmake/_version.pyi
cython_cmake/py.typed
cython_cmake/vendor.py
cython_cmake/cmake/FindCython.cmake
cython_cmake/cmake/UseCython.cmake
cython_cmake/cmake/__init__.py
cython_cmake-0.2.1.dist-info/METADATA
cython_cmake-0.2.1.dist-info/WHEEL
cython_cmake-0.2.1.dist-info/entry_points.txt
cython_cmake-0.2.1.dist-info/licenses/LICENSE
cython_cmake-0.2.1.dist-info/RECORD
