Metadata-Version: 2.3
Name: cython-cmake
Version: 0.2.1
Summary: CMake helpers for building Cython modules
Project-URL: Homepage, https://github.com/scikit-build/cython-cmake
Project-URL: Bug Tracker, https://github.com/scikit-build/cython-cmake/issues
Project-URL: Discussions, https://github.com/scikit-build/cython-cmake/discussions
Project-URL: Changelog, https://github.com/scikit-build/cython-cmake/releases
Author-email: Jean-Christophe Fillion-Robin <jchris.fillionr@kitware.com>
License: 
License-File: LICENSE
Classifier: Development Status :: 3 - Alpha
Classifier: Intended Audience :: Developers
Classifier: Intended Audience :: Science/Research
Classifier: License :: OSI Approved :: Apache Software License
Classifier: Operating System :: OS Independent
Classifier: Programming Language :: Python
Classifier: Programming Language :: Python :: 3
Classifier: Programming Language :: Python :: 3 :: Only
Classifier: Programming Language :: Python :: 3.8
Classifier: Programming Language :: Python :: 3.9
Classifier: Programming Language :: Python :: 3.10
Classifier: Programming Language :: Python :: 3.11
Classifier: Programming Language :: Python :: 3.12
Classifier: Programming Language :: Python :: 3.13
Classifier: Topic :: Scientific/Engineering
Classifier: Typing :: Typed
Requires-Python: >=3.8
Requires-Dist: cython
Requires-Dist: importlib-resources; python_version < '3.9'
Provides-Extra: docs
Requires-Dist: furo>=2023.08.17; extra == 'docs'
Requires-Dist: myst-parser>=0.13; extra == 'docs'
Requires-Dist: sphinx-autodoc-typehints; extra == 'docs'
Requires-Dist: sphinx-copybutton; extra == 'docs'
Requires-Dist: sphinx>=7.0; extra == 'docs'
Provides-Extra: test
Requires-Dist: pytest>=6; extra == 'test'
Requires-Dist: scikit-build-core; extra == 'test'
